discovery_client/__init__.py
discovery_client/discovery.py
discovery_client/util.py
onap_dcae_discovery_client-2.1.0.dist-info/DESCRIPTION.rst
onap_dcae_discovery_client-2.1.0.dist-info/METADATA
onap_dcae_discovery_client-2.1.0.dist-info/RECORD
onap_dcae_discovery_client-2.1.0.dist-info/WHEEL
onap_dcae_discovery_client-2.1.0.dist-info/metadata.json
onap_dcae_discovery_client-2.1.0.dist-info/top_level.txt
