Metadata-Version: 2.0
Name: onap-dcae-discovery-client
Version: 2.1.0
Summary: Library of discovery functionality
Home-page: UNKNOWN
Author: Michael Hwang
Author-email: UNKNOWN
License: Apache 2
Platform: UNKNOWN
Requires-Dist: python-consul (<1.0.0,>=0.6.0)
Requires-Dist: requests (<3.0.0,>=2.11.0)
Requires-Dist: six (>=1.10.0,<2.0.0)
